LICENSE.txt
MANIFEST.in
README
setup.py
silk/__init__.py
silk/deps.yaml
silk/devserver.py
silk/fabfile.py
silk/lib.py
silk/sock_http.py
silk/conf_templates/nginx.conf
silk/conf_templates/nginx_root.conf
silk/conf_templates/supervisord.conf
silk/conf_templates/supervisord_root.conf
silk/prereqs/distribute-0.6.21.tar.gz
silk/prereqs/pip-1.0.2.tar.gz
silk/site_templates/deps.yaml
silk/site_templates/fabfile.py
silk/site_templates/site.yaml
silk/site_templates/roles/dev.yaml
silk/site_templates/roles/production.yaml
silk/site_templates/roles/staging.yaml
silk_deployment.egg-info/PKG-INFO
silk_deployment.egg-info/SOURCES.txt
silk_deployment.egg-info/dependency_links.txt
silk_deployment.egg-info/entry_points.txt
silk_deployment.egg-info/requires.txt
silk_deployment.egg-info/top_level.txt