Metadata-Version: 1.0
Name: silk-deployment
Version: 0.3.14
Summary: A Fabric-based tool for deploying WSGI apps on an Ubuntu/Nginx/Supervisord/Gunicorn stack.
Home-page: http://bits.btubbs.com/silk-deployment
Author: Brent Tubbs
Author-email: brent.tubbs@gmail.com
License: LICENSE.txt
Platform: UNKNOWN
